OCRMyManga
