Metadata-Version: 2.1
Name: ocrmymanga
Version: 0.15
Summary: A handy tool for OCRing manga
License-File: LICENSE
